xmpy_ctp-1.0.3.dist-info/METADATA
xmpy_ctp-1.0.3.dist-info/WHEEL
xmpy_ctp/api/vnctpmd.cp312-win_amd64.pyd
xmpy_ctp/api/vnctpmd.cp312-win_amd64.lib
xmpy_ctp/api/vnctptd.cp312-win_amd64.pyd
xmpy_ctp/api/vnctptd.cp312-win_amd64.lib
xmpy_ctp/__init__.py
xmpy_ctp/api/__init__.py
xmpy_ctp/api/ctp_constant.py
xmpy_ctp/gateway/__init__.py
xmpy_ctp/gateway/ctp网关.py
xmpy_ctp/api/thostmduserapi_se.dll
xmpy_ctp/api/thosttraderapi_se.dll
xmpy_ctp-1.0.3.dist-info/RECORD
