Metadata-Version: 2.1
Name: xmpy_ctp
Version: 1.0.3
Summary: xmpy框架的CTP底层接口
Keywords: quant,quantitative,investment,trading,algotrading
Author-Email: bhzy <2024305928@qq.com>
License: MIT
Classifier: Development Status :: 5 - Production/Stable
Classifier: License :: OSI Approved :: MIT License
Classifier: Operating System :: Microsoft :: Windows
Classifier: Operating System :: POSIX :: Linux
Classifier: Operating System :: MacOS
Classifier: Programming Language :: Python :: 3
Classifier: Programming Language :: Python :: 3.10
Classifier: Programming Language :: Python :: 3.11
Classifier: Programming Language :: Python :: 3.12
Classifier: Programming Language :: Python :: 3.13
Classifier: Programming Language :: Python :: Implementation :: CPython
Classifier: Topic :: Office/Business :: Financial :: Investment
Classifier: Natural Language :: Chinese (Simplified)
Classifier: Typing :: Typed
Project-URL: Homepage, https://github.com/InkAbyss/xmpy_ctp
Project-URL: Issues, https://github.com/InkAbyss/xmpy_ctp/issues
Requires-Python: >=3.10
Requires-Dist: xmpy>=1.0.0
